{
  "generator-jhipster": {
    "applicationType": "monolith",
    "authenticationType": "jwt",
    "baseName": "wd-quote",
    "buildTool": "maven",
    "cacheProvider": "ehcache",
    "clientFramework": "vue",
    "clientTheme": "none",
    "creationTimestamp": 1693911487781,
    "cypressAudit": true,
    "cypressCoverage": null,
    "databaseType": "sql",
    "devDatabaseType": "postgresql",
    "devServerPort": 9060,
    "dtoSuffix": "DTO",
    "enableGradleEnterprise": null,
    "enableHibernateCache": true,
    "enableSwaggerCodegen": false,
    "enableTranslation": true,
    "entities": [
      "ProductCategory",
      "UnitOfMeasure",
      "UnitOfMeasureConversion",
      "Product",
      "Systema",
      "SystemModel",
      "Location",
      "Inventory",
      "Vendor",
      "DeliveryZone",
      "TaxAreaCode",
      "Language",
      "Customer",
      "CustomerContact",
      "MovementType",
      "Movement",
      "MovementDetails",
      "StockPosition"
    ],
    "entitySuffix": "",
    "gradleEnterpriseHost": null,
    "herokuAppName": "wdquote",
    "herokuDeployType": "jar",
    "herokuJavaVersion": "17",
    "jhiPrefix": "jhi",
    "jhipsterVersion": "8.0.0-beta.2",
    "jwtSecretKey": "OTcyOGViZDlhNDlkMGE5ZDg0NzY1MWE1NmNkZmJlMjYxNDY2OGZhMjczMmU5YTg5NTQ0YjdiODQ2Yjg4ZmZjOGFiZmIxN2NhZGViNzYxNWQ1Y2UyMmUwZDUzODE1ZWQ0MTAwNjRiZDQwY2E2MmNhMTk0OGQ2ODc4MjQzMTI4ODA=",
    "languages": ["en", "es"],
    "messageBroker": false,
    "microfrontend": false,
    "microfrontends": [],
    "nativeLanguage": "en",
    "packageFolder": "com/sapwd/wdquote",
    "packageName": "com.sapwd.wdquote",
    "pages": [],
    "prodDatabaseType": "postgresql",
    "reactive": false,
    "searchEngine": false,
    "serverPort": null,
    "serverSideOptions": ["websocket:spring-websocket"],
    "serviceDiscoveryType": false,
    "skipCheckLengthOfIdentifier": false,
    "skipClient": true,
    "skipFakeData": false,
    "skipUserManagement": false,
    "testFrameworks": ["cypress"],
    "websocket": "spring-websocket",
    "withAdminUi": true
  }
}
